{
  "title": "CardioNova — Investor Update",
  "subtitle": "Seed diligence summary · met Maya 6/18",
  "slides": [
    { "layout": "title", "title": "CardioNova", "subtitle": "AI triage for hospitals", "notes": "Open with the one-liner. Maya is cofounder/CEO, ex-Epic." },
    { "layout": "content", "title": "What they do", "bullets": [
      { "text": "Routes ER intake by acuity using vitals + patient history", "status": "verified", "source": "s1" },
      { "text": "Sells to mid-size hospital systems (not large academic centers)", "status": "manual", "source": "" }
    ], "notes": "Product claim is confirmed by their site; segment is my read from the conversation." },
    { "layout": "content", "title": "Traction", "bullets": [
      { "text": "3 hospital pilots signed this quarter", "status": "verified", "source": "Founder call notes 6/18 — Maya stated directly" },
      { "text": "Team of ~8, founders ex-Epic", "status": "manual", "source": "" },
      { "text": "Series B — stage and amount unconfirmed", "status": "needs_review", "source": "user note: 'maybe raising a Series B soon' — no amount, term sheet unknown" }
    ], "notes": "Lead with the pilots — that's the verified proof point." },
    { "layout": "stat", "title": "Runway", "stat": {
      "value": "[TK: verify months of runway]", "label": "Months of runway", "status": "needs_review", "source": "forgot to ask burn — not in notes" } },
    { "layout": "closing", "title": "Follow up", "subtitle": "Ask Maya about burn + how the pilots are going" }
  ],
  "sources": [
    { "id": "s1", "label": "CardioNova website", "url": "https://cardionova.example" }
  ]
}
