{
  "title": "Loomwork — Investor Update",
  "subtitle": "Diligence summary · met Devin, demo day 6/19",
  "theme": {
    "primary": "3A6B7E",
    "accent": "C8772E",
    "bg_dark": "171A1D",
    "bg_light": "F4F2EE",
    "text_dark": "20232A",
    "text_light": "F4F2EE",
    "warn": "C9892F",
    "muted": "8A8A82"
  },
  "slides": [
    { "layout": "title", "title": "Loomwork", "subtitle": "AI shift scheduling + route optimization for warehouses", "notes": "Met Devin at the warehouse-tech demo day, 6/19." },
    { "layout": "content", "title": "What they do", "bullets": [
      { "text": "Auto-schedules warehouse shifts and optimizes pick routes", "status": "verified", "source": "s1" },
      { "text": "Targets 3PLs and mid-size warehouse operators", "status": "manual", "source": "" }
    ], "notes": "Product is confirmed by the live demo; the segment is my read from the conversation." },
    { "layout": "content", "title": "Traction", "bullets": [
      { "text": "Two 3PL pilots currently running", "status": "manual", "source": "Devin stated at demo day 6/19 — not independently verified" },
      { "text": "Projected ~20% idle-labor reduction — a projection, NOT a measured result", "status": "needs_review", "source": "Devin: 'we think we can cut idle labor ~20%' — unmeasured; ask for pilot data" }
    ], "notes": "Be careful: the 20% is their projection, not a measured outcome." },
    { "layout": "stat", "title": "Headline metric", "stat": {
      "value": "[TK: measured idle-labor reduction]", "label": "Idle-labor reduction (founder projects ~20%, unverified)", "status": "needs_review", "source": "projection only — no measured pilot data in notes" } },
    { "layout": "content", "title": "Team & funding", "bullets": [
      { "text": "Team of ~5, ex-Flexport operations background", "status": "manual", "source": "Devin stated" },
      { "text": "Closed a small pre-seed round", "status": "manual", "source": "Devin stated; amount not given" },
      { "text": "Raising a seed round — target amount unknown", "status": "needs_review", "source": "[TK: seed target amount]" }
    ] },
    { "layout": "stat", "title": "Runway", "stat": {
      "value": "[TK: ask burn / runway]", "label": "Months of runway", "status": "needs_review", "source": "ARR and burn not captured in notes" } },
    { "layout": "closing", "title": "Follow up with Devin", "subtitle": "Pilot results · seed target · a reference customer" }
  ],
  "sources": [
    { "id": "s1", "label": "Live product demo, warehouse-tech demo day 6/19", "url": "" }
  ]
}
